JVP/__init__.py
JVP/marketData.py
JVP-0.0.1.dist-info/METADATA
JVP-0.0.1.dist-info/RECORD
JVP-0.0.1.dist-info/WHEEL
JVP-0.0.1.dist-info/top_level.txt
