Metadata-Version: 2.1
Name: JVP
Version: 0.0.1
Summary: A first draft of JVP tools
Home-page: UNKNOWN
Author: Jerome Petit
Author-email: jerome.petit@finastra.com
License: UNKNOWN
Platform: UNKNOWN
Requires-Dist: pandas
Requires-Dist: numpy
Requires-Dist: matplotlib
Requires-Dist: eikon
